extract_component/__init__.py
extract_component/data.py
extract_component/main.py
extract_component/test.py
extract_component/transform.py
extract_component/utils.py
open_clip/__init__.py
open_clip/bpe_simple_vocab_16e6.txt.gz
open_clip/factory.py
open_clip/openai.py
open_clip/pretrained.py
open_clip/timm_model.py
open_clip/tokenizer.py
open_clip/transform.py
open_clip/utils.py
open_clip/version.py
open_clip/loss/__init__.py
open_clip/loss/clip_loss.py
open_clip/loss/clip_mlmloss.py
open_clip/loss/moco_img_loss.py
open_clip/loss/test.py
open_clip/loss/test1.py
open_clip/loss/utils.py
open_clip/loss/wenlan_loss.py
open_clip/model/WenLan.py
open_clip/model/__init__.py
open_clip/model/base_model.py
open_clip/model/blocks.py
open_clip/model/config.py
open_clip/model/huggingface_model.py
open_clip/model/mlm.py
open_clip/model/mlm_img.py
open_clip/model/moco_img.py
open_clip/model/moco_text.py
open_clip/model/utils.py
open_clip/model_configs/RN101-quickgelu.json
open_clip/model_configs/RN101.json
open_clip/model_configs/RN50-mlm.json
open_clip/model_configs/RN50-quickgelu.json
open_clip/model_configs/RN50.json
open_clip/model_configs/RN50_ClinicalBERT.json
open_clip/model_configs/RN50_PubmedBERT.json
open_clip/model_configs/RN50_PubmedBERT_ROCO_finetune.json
open_clip/model_configs/RN50_UMLSBERT.json
open_clip/model_configs/RN50_width.json
open_clip/model_configs/RN50x16.json
open_clip/model_configs/RN50x4.json
training/dataset/__init__.py
training/dataset/csv_dataset.py
training/dataset/json_dataset.py
training/dataset/mlm.py
training/dataset/moco_dataset.py
training/dataset/test.py
training/dataset/utils.py
med_clip_weixiong-0.0.5.dist-info/LICENSE
med_clip_weixiong-0.0.5.dist-info/METADATA
med_clip_weixiong-0.0.5.dist-info/WHEEL
med_clip_weixiong-0.0.5.dist-info/top_level.txt
med_clip_weixiong-0.0.5.dist-info/RECORD
