Metadata-Version: 2.1
Name: med-clip-weixiong
Version: 0.0.5
Summary: MedCLIP
Home-page: https://gitee.com/lin_wei_hung/vlp
Author: weixiong
Author-email: wx_lin@outlook.com
License: UNKNOWN
Keywords: CLIP pretrained
Platform: UNKNOWN
Classifier: Development Status :: 3 - Alpha
Classifier: Intended Audience :: Education
Classifier: Intended Audience :: Science/Research
Classifier: License :: OSI Approved :: Apache Software License
Classifier: Programming Language :: Python :: 3.7
Classifier: Programming Language :: Python :: 3.8
Classifier: Programming Language :: Python :: 3.9
Classifier: Programming Language :: Python :: 3.10
Classifier: Topic :: Scientific/Engineering
Classifier: Topic :: Scientific/Engineering :: Artificial Intelligence
Classifier: Topic :: Software Development
Classifier: Topic :: Software Development :: Libraries
Classifier: Topic :: Software Development :: Libraries :: Python Modules
Requires-Python: >=3.7
Requires-Dist: torch (>=1.9)
Requires-Dist: torchvision
Requires-Dist: transformers (<=4.21.0)
Requires-Dist: ftfy
Requires-Dist: regex
Requires-Dist: tqdm
